{
    "$schema": "https://schema.management.azure.com/schemas/2019-04-01/deploymentTemplate.json#",
    "contentVersion": "0.0.0.5",
    "parameters": {
        "fontDoorBackend": { 
            "type": "array",
            "metadata": {
                "description": "List of backend apps domain name or public ips which will be part of the backend pool"
            }
         },
        "location": {
            "defaultValue": "eastus2",
            "type": "string",
            "allowedValues": [
                "australiaeast",
                "canadacentral",
                "centralus",
                "eastus",
                "eastus2",
                "westus2",
                "francecentral",
                "germanywestcentral",
                "northeurope",
                "southafricanorth",
                "southcentralus",
                "uksouth",
                "westeurope",
                "japaneast",
                "southeastasia",
                "brazilsouth",
                "southcentralus"
            ],
            "metadata": {
                "description": "AKS Service, Node Pool, and supporting services (KeyVault, App Gateway, etc) region. This needs to be the same region as the vnet provided in these parameters."
            }
        },
        "geoRedundancyLocation": {
            "defaultValue": "centralus",
            "type": "string",
            "allowedValues": [
                "australiasoutheast",
                "canadaeast",
                "eastus2",
                "westus",
                "centralus",
                "westcentralus",
                "francesouth",
                "germanynorth",
                "westeurope",
                "ukwest",
                "northeurope",
                "japanwest",
                "southafricawest",
                "northcentralus",
                "eastasia",
                "eastus",
                "westus2",
                "francecentral",
                "uksouth",
                "japaneast",
                "southeastasia",
                "brazilsouth",
                "southcentralus"
            ],
            "metadata": {
                "description": "For Azure resources that support native geo-redunancy, provide the location the redundant service will have its secondary. Should be different than the location parameter and ideally should be a paired region - https://docs.microsoft.com/azure/best-practices-availability-paired-regions. This region does not need to support availability zones."
            }
        }
    },
    "variables": {
        "subRgUniqueString": "[uniqueString('aks',subscription().subscriptionId, resourceGroup().id)]",

        "logAnalyticsWorkspaceName": "[concat('la-', variables('subRgUniqueString'))]",
        "defaultAcrName": "[concat('acraks', variables('subRgUniqueString'))]",

        "acrPrivateDnsZonesName": "privatelink.azurecr.io",

        "frontDoorName": "[concat('bicycle', variables('subRgUniqueString'))]",
        "frontDoorPolicyName": "[concat('policyfd', variables('subRgUniqueString'))]"
    },
    "resources": [
        {
            "type": "Microsoft.Network/privateDnsZones",
            "apiVersion": "2020-06-01",
            "name": "[variables('acrPrivateDnsZonesName')]",
            "location": "global",
            "comments": "Enabling Azure Container Registry Private Link on vnet.",
            "properties": {}
        },
        {
            "type": "Microsoft.OperationalInsights/workspaces",
            "apiVersion": "2020-08-01",
            "name": "[variables('logAnalyticsWorkspaceName')]",
            "location": "[parameters('location')]",
            "properties": {
                "sku": {
                    "name": "PerGB2018"
                },
                "retentionInDays": 30
            },
            "resources": [
                {
                    "type": "savedSearches",
                    "apiVersion": "2020-08-01",
                    "name": "AllPrometheus",
                    "dependsOn": [
                        "[concat('Microsoft.OperationalInsights/workspaces/', variables('logAnalyticsWorkspaceName'))]"
                    ],
                    "properties": {
                        "eTag": "*",
                        "category": "Prometheus",
                        "displayName": "All collected Prometheus information",
                        "query": "InsightsMetrics | where Namespace == \"prometheus\"",
                        "version": 1
                    }
                },
                {
                    "type": "savedSearches",
                    "apiVersion": "2020-08-01",
                    "name": "ForbiddenReponsesOnIngress",
                    "dependsOn": [
                        "[concat('Microsoft.OperationalInsights/workspaces/', variables('logAnalyticsWorkspaceName'))]"
                    ],
                    "properties": {
                        "eTag": "*",
                        "category": "Prometheus",
                        "displayName": "Increase number of forbidden response on the Ingress Controller",
                        "query": "let value = toscalar(InsightsMetrics | where Namespace == \"prometheus\" and Name == \"traefik_entrypoint_requests_total\" | where parse_json(Tags).code == 403 | summarize Value = avg(Val) by bin(TimeGenerated, 5m) | summarize min = min(Value)); InsightsMetrics | where Namespace == \"prometheus\" and Name == \"traefik_entrypoint_requests_total\" | where parse_json(Tags).code == 403 | summarize AggregatedValue = avg(Val)-value by bin(TimeGenerated, 5m) | order by TimeGenerated | render barchart",
                        "version": 1
                    }
                },
                {
                    "type": "savedSearches",
                    "apiVersion": "2020-08-01",
                    "name": "NodeRebootRequested",
                    "dependsOn": [
                        "[concat('Microsoft.OperationalInsights/workspaces/', variables('logAnalyticsWorkspaceName'))]"
                    ],
                    "properties": {
                        "eTag": "*",
                        "category": "Prometheus",
                        "displayName": "Nodes reboot required by kured",
                        "query": "InsightsMetrics | where Namespace == \"prometheus\" and Name == \"kured_reboot_required\" | where Val > 0",
                        "version": 1
                    }
                }
            ]
        },
        {
            "type": "Microsoft.OperationsManagement/solutions",
            "apiVersion": "2015-11-01-preview",
            "name": "[concat('ContainerInsights(', variables('logAnalyticsWorkspaceName'),')')]",
            "location": "[parameters('location')]",
            "dependsOn": [
                "[resourceId('Microsoft.OperationalInsights/workspaces', variables('logAnalyticsWorkspaceName'))]"
            ],
            "properties": {
                "workspaceResourceId": "[resourceId('Microsoft.OperationalInsights/workspaces', variables('logAnalyticsWorkspaceName'))]"
            },
            "plan": {
                "name": "[concat('ContainerInsights(', variables('logAnalyticsWorkspaceName'),')')]",
                "product": "OMSGallery/ContainerInsights",
                "promotionCode": "",
                "publisher": "Microsoft"
            }
        },
        {
            "type": "Microsoft.OperationsManagement/solutions",
            "apiVersion": "2015-11-01-preview",
            "name": "[concat('AzureAppGatewayAnalytics(', variables('logAnalyticsWorkspaceName'),')')]",
            "location": "[parameters('location')]",
            "dependsOn": [
                "[resourceId('Microsoft.OperationalInsights/workspaces', variables('logAnalyticsWorkspaceName'))]"
            ],
            "properties": {
                "workspaceResourceId": "[resourceId('Microsoft.OperationalInsights/workspaces', variables('logAnalyticsWorkspaceName'))]"
            },
            "plan": {
                "name": "[concat('AzureAppGatewayAnalytics(', variables('logAnalyticsWorkspaceName'),')')]",
                "product": "OMSGallery/AzureAppGatewayAnalytics",
                "promotionCode": "",
                "publisher": "Microsoft"
            }
        },
        {
            "type": "Microsoft.OperationsManagement/solutions",
            "apiVersion": "2015-11-01-preview",
            "name": "[concat('KeyVaultAnalytics(', variables('logAnalyticsWorkspaceName'),')')]",
            "location": "[parameters('location')]",
            "dependsOn": [
                "[resourceId('Microsoft.OperationalInsights/workspaces', variables('logAnalyticsWorkspaceName'))]"
            ],
            "properties": {
                "workspaceResourceId": "[resourceId('Microsoft.OperationalInsights/workspaces', variables('logAnalyticsWorkspaceName'))]"
            },
            "plan": {
                "name": "[concat('KeyVaultAnalytics(', variables('logAnalyticsWorkspaceName'),')')]",
                "product": "OMSGallery/KeyVaultAnalytics",
                "promotionCode": "",
                "publisher": "Microsoft"
            }
        },
        {
            "type": "Microsoft.ContainerRegistry/registries",
            "apiVersion": "2020-11-01-preview",
            "name": "[variables('defaultAcrName')]",
            "location": "[parameters('location')]",
            "sku": {
                "name": "Premium"
            },
            "properties": {
                "adminUserEnabled": false,
                "networkRuleSet": {
                    "defaultAction": "Deny",
                    "virtualNetworkRules": [],
                    "ipRules": []
                },
                "policies": {
                    "quarantinePolicy": {
                        "status": "disabled"
                    },
                    "trustPolicy": {
                        "type": "Notary",
                        "status": "disabled"
                    },
                    "retentionPolicy": {
                        "days": 15,
                        "status": "enabled"
                    }
                },
                "publicNetworkAccess": "Disabled",
                "encryption": {
                    "status": "disabled"
                },
                "dataEndpointEnabled": true,
                "networkRuleBypassOptions": "AzureServices",
                "zoneRedundancy": "Disabled"
            },
            "resources": [
                {
                    "type": "replications",
                    "apiVersion": "2019-05-01",
                    "name": "[parameters('geoRedundancyLocation')]",
                    "location": "[parameters('geoRedundancyLocation')]",
                    "dependsOn": [
                        "[variables('defaultAcrName')]"
                    ],
                    "properties": {}
                },
                {
                    "type": "providers/diagnosticSettings",
                    "apiVersion": "2017-05-01-preview",
                    "name": "Microsoft.Insights/default",
                    "dependsOn": [
                        "[resourceId('Microsoft.ContainerRegistry/registries', variables('defaultAcrName'))]",
                        "[resourceId('Microsoft.OperationalInsights/workspaces', variables('logAnalyticsWorkspaceName'))]"
                    ],
                    "properties": {
                        "workspaceId": "[resourceId('Microsoft.OperationalInsights/workspaces', variables('logAnalyticsWorkspaceName'))]",
                        "metrics": [
                            {
                                "timeGrain": "PT1M",
                                "category": "AllMetrics",
                                "enabled": true
                            }
                        ],
                        "logs": [
                            {
                                "category": "ContainerRegistryRepositoryEvents",
                                "enabled": true
                            },
                            {
                                "category": "ContainerRegistryLoginEvents",
                                "enabled": true
                            }
                        ]
                    }
                }
            ]
        },
        {
            "name": "PodFailedScheduledQuery",
            "type": "microsoft.insights/scheduledqueryrules",
            "location": "global",
            "apiVersion": "2021-02-01-preview",
            "tags": {},
            "properties": {
                "description": "Example from: https://docs.microsoft.com/azure/azure-monitor/insights/container-insights-alerts",
                "severity": 3,
                "enabled": true,
                "evaluationFrequency": "PT5M",
                "scopes": [
                    "[subscription().id]"
                ],
                "windowSize": "PT5M",
                "overrideQueryTimeRange": "P2D",
                "criteria": {
                    "allOf": [
                        {
                            "query": "let trendBinSize = 1m;\r\nKubePodInventory\r\n| distinct ClusterName, TimeGenerated, _ResourceId\r\n| summarize ClusterSnapshotCount = count() by bin(TimeGenerated, trendBinSize), ClusterName, _ResourceId\r\n| join hint.strategy=broadcast (\r\nKubePodInventory\r\n| distinct ClusterName, Computer, PodUid, TimeGenerated, PodStatus\r\n| summarize TotalCount = count(),\r\nPendingCount = sumif(1, PodStatus =~ \"Pending\"),\r\nRunningCount = sumif(1, PodStatus =~ \"Running\"),\r\nSucceededCount = sumif(1, PodStatus =~ \"Succeeded\"),\r\nFailedCount = sumif(1, PodStatus =~ \"Failed\")\r\nby ClusterName, bin(TimeGenerated, trendBinSize)\r\n)\r\non ClusterName, TimeGenerated\r\n| extend UnknownCount = TotalCount - PendingCount - RunningCount - SucceededCount - FailedCount\r\n| project TimeGenerated,\r\nClusterName,\r\n_ResourceId,\r\nTotalCount = todouble(TotalCount) / ClusterSnapshotCount,\r\nPendingCount = todouble(PendingCount) / ClusterSnapshotCount,\r\nRunningCount = todouble(RunningCount) / ClusterSnapshotCount,\r\nSucceededCount = todouble(SucceededCount) / ClusterSnapshotCount,\r\nFailedCount = todouble(FailedCount) / ClusterSnapshotCount,\r\nUnknownCount = todouble(UnknownCount) / ClusterSnapshotCount",
                            "timeAggregation": "Average",
                            "metricMeasureColumn": "FailedCount",
                            "dimensions": [
                                {
                                    "name": "ClusterName",
                                    "operator": "Include",
                                    "values": [
                                        "*"
                                    ]
                                }
                            ],
                            "resourceIdColumn": "_ResourceId",
                            "operator": "GreaterThan",
                            "threshold": 3,
                            "failingPeriods": {
                                "numberOfEvaluationPeriods": 1,
                                "minFailingPeriodsToAlert": 1
                            }
                        }
                    ]
                }
            }
        },
        {
            "type": "microsoft.insights/activityLogAlerts",
            "apiVersion": "2017-04-01",
            "name": "AllAzureAdvisorAlert",
            "location": "Global",
            "properties": {
                "scopes": [
                    "[subscription().id]"
                ],
                "condition": {
                    "allOf": [
                        {
                            "field": "category",
                            "equals": "Recommendation"
                        },
                        {
                            "field": "operationName",
                            "equals": "Microsoft.Advisor/recommendations/available/action"
                        }
                    ]
                },
                "actions": {
                    "actionGroups": [
                    ]
                },
                "enabled": true,
                "description": "All azure advisor alerts"
            }
        },
        {
            "type": "Microsoft.Network/frontdoorwebapplicationfirewallpolicies",
            "apiVersion": "2020-04-01",
            "name":  "[variables('frontDoorPolicyName')]",
            "location": "Global",
            "properties": {
                "policySettings": {
                    "enabledState": "Enabled",
                    "mode": "Prevention",
                    "customBlockResponseStatusCode": 403
                },
                "customRules": {
                    "rules": []
                },
                "managedRules": {
                    "managedRuleSets": [
                        {
                            "ruleSetType": "DefaultRuleSet",
                            "ruleSetVersion": "1.0",
                            "ruleGroupOverrides": [],
                            "exclusions": []
                        }
                    ]
                }
            }
        },
        {
            "type": "Microsoft.Network/frontdoors",
            "apiVersion": "2020-05-01",
            "name": "[variables('frontDoorName')]",
            "location": "Global",
            "dependsOn": [
                "[resourceId('Microsoft.Network/frontdoorwebapplicationfirewallpolicies', variables('frontDoorPolicyName'))]"
            ],
            "properties": {
                "resourceState": "Enabled",
                "backendPools": [
                    {
                        "name": "MultiClusterBackendPool",
                        "properties": {
                            "copy": [
                               {
                                    "name": "backends",
                                    "count": "[length(parameters('fontDoorBackend'))]",
                                    "input": {
                                        "address": "[parameters('fontDoorBackend')[copyIndex('backends')]]",
                                        "httpPort": 80,
                                        "httpsPort": 443,
                                        "priority": 1,
                                        "weight": 50,
                                        "enabledState": "Enabled",
                                        "backendHostHeader": "[parameters('fontDoorBackend')[copyIndex('backends')]]"
                                    }
                                }
                            ],
                            "healthProbeSettings": {
                                "id": "[concat(resourceId('Microsoft.Network/frontdoors', variables('frontDoorName')), '/HealthProbeSettings/healthProbeSettings')]"
                            },
                            "loadBalancingSettings": {
                                "id": "[concat(resourceId('Microsoft.Network/frontdoors', variables('frontDoorName')), '/LoadBalancingSettings/loadBalancingSettings')]"
                            },
                            "resourceState": "Enabled"
                        }
                    }
                ],
                "healthProbeSettings": [
                    {
                        "name": "healthProbeSettings",
                        "properties": {
                            "intervalInSeconds": 30,
                            "path": "/favicon.ico",
                            "protocol": "Https",
                            "resourceState": "Enabled",
                            "enabledState": "Enabled",
                            "healthProbeMethod": "HEAD"
                        }
                    }
                ],
                "frontendEndpoints": [
                    {
                        "name": "MultiClusterFrontendEndpoint",
                        "properties": {
                            "hostName": "[concat(variables('frontDoorName'), '.azurefd.net')]",
                            "sessionAffinityEnabledState": "Disabled",
                            "sessionAffinityTtlSeconds": 0,
                            "webApplicationFirewallPolicyLink": {
                                "id": "[resourceId('Microsoft.Network/frontdoorwebapplicationfirewallpolicies', variables('frontDoorPolicyName'))]"
                            },
                            "resourceState": "Enabled"
                        }
                    }
                ],
                "loadBalancingSettings": [
                    {
                        "name": "loadBalancingSettings",
                        "properties": {
                            "additionalLatencyMilliseconds": 0,
                            "sampleSize": 4,
                            "successfulSamplesRequired": 2,
                            "resourceState": "Enabled"
                        }
                    }
                ],
                "routingRules": [
                    {
                        "name": "MultiClusterRule",
                        "properties": {
                            "frontendEndpoints": [
                                {
                                    "id": "[concat(resourceId('Microsoft.Network/frontdoors',  variables('frontDoorName')), concat('/FrontendEndpoints/',  'MultiClusterFrontendEndpoint'))]"
                                }
                            ],
                            "acceptedProtocols": [
                                "Https"
                            ],
                            "patternsToMatch": [
                                "/*"
                            ],
                            "enabledState": "Enabled",
                            "resourceState": "Enabled",
                            "routeConfiguration": {
                                "@odata.type": "#Microsoft.Azure.FrontDoor.Models.FrontdoorForwardingConfiguration",
                                "forwardingProtocol": "HttpsOnly",
                                "backendPool": {
                                    "id": "[concat(resourceId('Microsoft.Network/frontdoors',  variables('frontDoorName')), concat('/backendPools/',  'MultiClusterBackendPool'))]"
                                }
                            }
                        }
                    }
                ],
                "backendPoolsSettings": {
                    "enforceCertificateNameCheck": "Enabled",
                    "sendRecvTimeoutSeconds": 30
                },
                "enabledState": "Enabled",
                "friendlyName": "[variables('frontDoorName')]"
            }
        }
    ],
    "outputs": {
        "logAnalyticsWorkspaceId": {
            "type": "string",
            "value": "[resourceId('Microsoft.OperationalInsights/workspaces', variables('logAnalyticsWorkspaceName'))]"
        },
        "containerRegistryId": {
            "type": "string",
            "value": "[resourceId('Microsoft.ContainerRegistry/registries', variables('defaultAcrName'))]"
        },
        "containerRegistryName": {
            "type": "string",
            "value": "[variables('defaultAcrName')]"
        },
        "acrPrivateDnsZonesId": {
            "type": "string",
            "value": "[resourceId('Microsoft.Network/privateDnsZones', variables('acrPrivateDnsZonesName'))]"
        },
        "fqdn": {
            "type": "string",
            "value": "[concat(variables('frontDoorName'), '.azurefd.net')]"
        }
    }
}
